dassco_utils/__init__.py
dassco_utils/guid/__init__.py
dassco_utils/guid/main.py
dassco_utils/messaging/__init__.py
dassco_utils/messaging/async_rabbitmq_client.py
dassco_utils/messaging/exceptions.py
dassco_utils/messaging/orchestration_client.py
dassco_utils/messaging/rabbitmq_client.py
dassco_utils/metadata/__init__.py
dassco_utils/metadata/metadata_handler.py
dassco_utils/metadata/models.py
dassco_utils-1.0.7.dist-info/licenses/LICENSE
examples/__init__.py
examples/example_metadata.py
examples/async_rabbitmq_client/__init__.py
examples/async_rabbitmq_client/example_consumers.py
examples/rabbitmq_client/__init__.py
examples/rabbitmq_client/example_consumers.py
examples/rabbitmq_client/example_exception.py
test/__init__.py
test/test_guid.py
test/test_messaging.py
test/test_metadata.py
dassco_utils-1.0.7.dist-info/METADATA
dassco_utils-1.0.7.dist-info/WHEEL
dassco_utils-1.0.7.dist-info/top_level.txt
dassco_utils-1.0.7.dist-info/RECORD
